michie/__init__.py
michie/factory.py
michie/object.py
michie/serialize.py
michie/worker.py
michie/world.py
michie/hooks/__init__.py
michie/hooks/hook.py
michie/mappers/__init__.py
michie/mappers/add_tick.py
michie/mappers/communication_neighbours.py
michie/mappers/condition_neighbours.py
michie/mappers/distances.py
michie/mappers/globalmapper.py
michie/mappers/neighbours.py
michie/mappers/range_and_bearing.py
michie/mappers/statemapper.py
michie/sprites/__init__.py
michie/sprites/drone.py
michie/sprites/heading.py
michie/sprites/point.py
michie/sprites/sprite.py
michie/transitions/__init__.py
michie/transitions/move.py
michie/transitions/transition.py
michie/utils/__init__.py
michie/utils/utils.py
michie/utils/init/__init__.py
michie/utils/init/init.py
michie-0.2.2.dist-info/LICENSE
michie-0.2.2.dist-info/METADATA
michie-0.2.2.dist-info/WHEEL
michie-0.2.2.dist-info/top_level.txt
michie-0.2.2.dist-info/RECORD
