Metadata-Version: 2.1
Name: michie
Version: 0.2.2
Home-page: 
Author: Federico A. Galatolo
Author-email: federico.galatolo@ing.unipi.it
Classifier: Programming Language :: Python :: 3.8
Classifier: License :: OSI Approved :: GNU General Public License v3 (GPLv3)
Classifier: Operating System :: OS Independent
Classifier: Topic :: Scientific/Engineering
Classifier: Intended Audience :: Science/Research
Classifier: Development Status :: 4 - Beta
License-File: LICENSE
Requires-Dist: tqdm (>=4.64.1)
Requires-Dist: pygame (>=2.1.2)
Requires-Dist: numpy (>=1.23.4)
Requires-Dist: schema (>=0.7.5)
Requires-Dist: scipy (>=1.9.2)
Requires-Dist: orjson (>=3.8.0)
Requires-Dist: lru-dict (==1.1.8)
Requires-Dist: flatdict (==4.0.1)
